cdiscount_parser/__init__.py
cdiscount_parser/price_parser.py
cdiscountpriceparser-0.0.2.dist-info/METADATA
cdiscountpriceparser-0.0.2.dist-info/WHEEL
cdiscountpriceparser-0.0.2.dist-info/top_level.txt
cdiscountpriceparser-0.0.2.dist-info/RECORD
