Metadata-Version: 2.1
Name: cdiscountpriceparser
Version: 0.0.2
Summary: price parser of cdiscount product.
Home-page: https://github.com/pierredarrieutort/cdiscrap
Author: mathieudaix, pierredarrieutort
Author-email: mathieudaixpro@gmail.com, p.darrieutort@outlook.fr
License: UNKNOWN
Platform: UNKNOWN
Requires-Dist: beautifulsoup4 (~=4.9.0)
Requires-Dist: urllib3 (~=1.25.9)
Requires-Dist: regex (~=2020.4.4)
Provides-Extra: dev
Requires-Dist: pytest (>=5.4.1) ; extra == 'dev'
